iptv_spider/__init__.py
iptv_spider/__main__.py
iptv_spider/channel.py
iptv_spider/logger.py
iptv_spider/m3u.py
iptv_spider/main.py
iptv_spider/verify.py
iptv_spider-0.2.3.dist-info/LICENSE.txt
iptv_spider-0.2.3.dist-info/METADATA
iptv_spider-0.2.3.dist-info/WHEEL
iptv_spider-0.2.3.dist-info/entry_points.txt
iptv_spider-0.2.3.dist-info/top_level.txt
iptv_spider-0.2.3.dist-info/RECORD
