Metadata-Version: 2.1
Name: iptv-spider
Version: 0.2.3
Summary: A Python project for get iptv channels with the best network speed.
Author-email: Win2er <qq125594648@gmail.com>
Maintainer-email: Win2er <qq125594648@gmail.com>
License: MIT License
Project-URL: Homepage, https://github.com/malidong/iptv_spider
Project-URL: Bug Reports, https://github.com/malidong/iptv_spider/issues
Project-URL: Say Thanks!, https://hooks.slack.com/services/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
Project-URL: Source, https://github.com/malidong/iptv_spider.git
Keywords: iptv,m3u8,brandwidth,speed
Classifier: Development Status :: 3 - Alpha
Classifier: Intended Audience :: Developers
Classifier: Topic :: Utilities
Classifier: License :: OSI Approved :: MIT License
Classifier: Programming Language :: Python :: 3.11
Classifier: Programming Language :: Python :: 3.12
Classifier: Programming Language :: Python :: 3.13
Classifier: Programming Language :: Python :: 3 :: Only
Requires-Python: >=3.11
License-File: LICENSE.txt
Requires-Dist: m3u8==6.0.0
Requires-Dist: requests==2.32.3
Provides-Extra: dev
Requires-Dist: check-manifest; extra == "dev"
Requires-Dist: pylint; extra == "dev"
Requires-Dist: flake8; extra == "dev"
Provides-Extra: test
Requires-Dist: coverage; extra == "test"
